libyate/__init__.py
libyate/engine.py
libyate/extmodule.py
libyate/rmanager.py
libyate/type.py
libyate-1.0.dist-info/DESCRIPTION.rst
libyate-1.0.dist-info/METADATA
libyate-1.0.dist-info/metadata.json
libyate-1.0.dist-info/pbr.json
libyate-1.0.dist-info/RECORD
libyate-1.0.dist-info/top_level.txt
libyate-1.0.dist-info/WHEEL
