Metadata-Version: 2.0
Name: libyate
Version: 1.0
Summary: Python library for developing Yate external applications
Home-page: http://bitbucket.org/asenci/libyate
Author: Andre Sencioles Vitorio Oliveira
Author-email: andre@bcp.net.br
License: ISC License
Keywords: yate
Platform: any
Classifier: Natural Language :: English
Classifier: Operating System :: MacOS :: MacOS X
Classifier: Operating System :: POSIX
Classifier: Operating System :: POSIX :: BSD
Classifier: Operating System :: POSIX :: Linux
Classifier: Operating System :: Microsoft :: Windows
Classifier: Programming Language :: Python
Classifier: Programming Language :: Python :: 2
Classifier: Programming Language :: Python :: 2.6
Classifier: Programming Language :: Python :: 2.7
Classifier: Programming Language :: Python :: Implementation :: CPython
